arbiter/arbiter.v
module arbiter(clk, rest_n, req_0, req_1, sig_0, sig_1);

    input wire clk, rest_n, req_0, req_1;

    output reg sig_0, sig_1;


    parameter IDLE = 2'b00, AGENT_0 = 2'b01, AGENT_1 = 2'b10;

    reg [1:0] state;

    always @(posedge clk or negedge rest_n) begin
        if (!rest_n) begin
            state <= IDLE;
            sig_0 <= 0;
            sig_1 <= 0;
        end else begin
            case (state)
                IDLE: begin
                    if (req_0) begin
                        state <= AGENT_0;
                    end
                    else if (!req_0 && req_1) begin
                        state <= AGENT_1;
                    end
                end
                AGENT_0: begin
                    if(!req_0) begin
                        state <= IDLE;
                    end
                end
                AGENT_1: begin
                    if(!req_1) begin
                        state <= IDLE;
                    end
                end
                default: state <= IDLE;
            endcase

        end

    end

    always@(posedge clk) begin
        case (state)
            AGENT_0: begin
                sig_0 <= 1;
                sig_1 <= 0;
            end
            AGENT_1: begin
                sig_0 <= 0;
                sig_1 <= 1;
            end
            default: begin
                sig_0 <= 0;
                sig_1 <= 0;
            end
        endcase
    end

endmodule

arbiter/arbiter_tb.v
module arbiter_tb;

    reg clk, rest_n, req_0, req_1;
    wire sig_0, sig_1;
    parameter PERIOD = 10;

    arbiter U0(
        .clk(clk),
        .rest_n(rest_n),
        .req_0(req_0),
        .req_1(req_1),
        .sig_0(sig_0),
        .sig_1(sig_1)
    );

    always #((PERIOD / 2)) clk = ~clk;


    initial begin
        $dumpfile("arbiter.vcd");
        $dumpvars(0, arbiter_tb);

        clk = 0;
        rest_n = 0;
        req_0 = 0;
        req_1 = 0;

        #6 rest_n = 1;
        //#15 rest_n = 0;
        #8 req_0 = 1;
        #8 req_0 = 0;
        #8 req_1 = 1;
        #4 {req_0, req_1} = 2'b11;
        #6 req_1 = 1;
        #4 {req_0, req_1} = 2'b00;
        #6 {req_0, req_1} = 2'b01;
        #20 $finish;
    end

    always @(posedge clk) begin
        $display("At time %0t : req_0 = %0b, req_1 = %0b, sig_0 = %0b, sig_1 = %0b", $time, req_0, req_1, sig_0, sig_1);
    end

endmodule

arbiter/arbiter.vcd
$date
	Sun Mar  3 00:50:26 2024
$end
$version
	Icarus Verilog
$end
$timescale
	1s
$end
$scope module arbiter_tb $end
$var wire 1 ! sig_1 $end
$var wire 1 " sig_0 $end
$var reg 1 # clk $end
$var reg 1 $ req_0 $end
$var reg 1 % req_1 $end
$var reg 1 & rest_n $end
$scope module U0 $end
$var wire 1 # clk $end
$var wire 1 $ req_0 $end
$var wire 1 % req_1 $end
$var wire 1 & rest_n $end
$var reg 1 " sig_0 $end
$var reg 1 ! sig_1 $end
$var reg 2 ' state [1:0] $end
$upscope $end
$upscope $end
$enddefinitions $end
#0
$dumpvars
b0 '
0&
0%
0$
0#
0"
0!
$end
#5
1#
#6
1&
#10
0#
#14
1$
#15
b1 '
1#
#20
0#
#22
0$
#25
1"
b0 '
1#
#30
0#
1%
#34
1$
#35
0"
b1 '
1#
#40
0#
#44
0$
0%
#45
1"
b0 '
1#
#50
0#
1%
#55
0"
b10 '
1#
#60
0#
#65
1!
1#
